{
  "0": {
    "basicblocks": 23,
    "calls": "1 1 1",
    "file": "bnn.cpp",
    "fileloc": 75,
    "instructions": 257,
    "loads": {
      "L": 17
    },
    "name": "feedforward",
    "stores": {
      "L": 21
    },
    "total_instructions": 389
  },
  "1": {
    "basicblocks": 11,
    "calls": "",
    "file": "bnn.cpp",
    "fileloc": 47,
    "instructions": 44,
    "loads": {
      "L": 3
    },
    "name": "matmul_xnor",
    "stores": {
      "L": 3
    },
    "total_instructions": 44
  }
}